ratelimit/__init__.py
ratelimit/decorators.py
ratelimit/exception.py
deckar01_ratelimit-3.0.2.dist-info/LICENSE.txt
deckar01_ratelimit-3.0.2.dist-info/METADATA
deckar01_ratelimit-3.0.2.dist-info/WHEEL
deckar01_ratelimit-3.0.2.dist-info/top_level.txt
deckar01_ratelimit-3.0.2.dist-info/RECORD
