Metadata-Version: 2.1
Name: deckar01-ratelimit
Version: 3.0.2
Summary: API rate limit decorator
Home-page: https://github.com/deckar01/ratelimit
Author: Jared Deckard
Author-email: jared@shademaps.com
License: MIT
Keywords: ratelimit,api,decorator
Platform: UNKNOWN
Classifier: Development Status :: 5 - Production/Stable
Classifier: Intended Audience :: Developers
Classifier: License :: OSI Approved :: MIT License
Classifier: Natural Language :: English
Classifier: Programming Language :: Python
Classifier: Topic :: Software Development
Requires-Python: >3.6.0
License-File: LICENSE.txt
